cryocare/__init__.py
cryocare/bibtex.py
cryocare/constants.py
cryocare/icon.png
cryocare/objects.py
cryocare/protocols.conf
cryocare/utils.py
cryocare/protocols/__init__.py
cryocare/protocols/protocol_base.py
cryocare/protocols/protocol_load_model.py
cryocare/protocols/protocol_predict.py
cryocare/protocols/protocol_training.py
cryocare/tests/__init__.py
cryocare/tests/test_cryoCARE_workflow.py
scipion_em_cryocare-4.2.2.dist-info/LICENSE
scipion_em_cryocare-4.2.2.dist-info/METADATA
scipion_em_cryocare-4.2.2.dist-info/WHEEL
scipion_em_cryocare-4.2.2.dist-info/entry_points.txt
scipion_em_cryocare-4.2.2.dist-info/top_level.txt
scipion_em_cryocare-4.2.2.dist-info/RECORD
